LICENSE.txt
MANIFEST.in
README.rst
setup.cfg
setup.py
django_world_languages.egg-info/PKG-INFO
django_world_languages.egg-info/SOURCES.txt
django_world_languages.egg-info/dependency_links.txt
django_world_languages.egg-info/not-zip-safe
django_world_languages.egg-info/requires.txt
django_world_languages.egg-info/top_level.txt
world_languages/__init__.py
world_languages/admin.py
world_languages/apps.py
world_languages/conf.py
world_languages/managers.py
world_languages/models.py
world_languages/tests.py
world_languages/utils.py
world_languages/views.py
world_languages/management/commands/__init__.py
world_languages/management/commands/world_languages.py
world_languages/migrations/0001_initial.py
world_languages/migrations/__init__.py
world_languages/tests/data/aghu1253.yaml
world_languages/tests/data/anti1245.yaml
world_languages/tests/data/aram1237.yaml
world_languages/tests/data/aves1237.yaml
world_languages/tests/data/ayut1236.yaml
world_languages/tests/data/bain1259.yaml
world_languages/tests/data/bali1278.yaml
world_languages/tests/data/cent2083.yaml
world_languages/tests/data/chau1259.yaml
world_languages/tests/data/chep1243.yaml
world_languages/tests/data/esto1258.yaml
world_languages/tests/data/kant1249.yaml
world_languages/tests/data/keii1239.yaml
world_languages/tests/data/kore1280.yaml
world_languages/tests/data/mari1426.yaml
world_languages/tests/data/mode1248.yaml
world_languages/tests/data/mtir1236.yaml
world_languages/tests/data/nege1244.yaml
world_languages/tests/data/nepa1252.yaml
world_languages/tests/data/plai1235.yaml
world_languages/tests/data/poli1260.yaml
world_languages/tests/data/sama1313.yaml
world_languages/tests/data/sans1272.yaml
world_languages/tests/data/suda1236.yaml
world_languages/tests/data/tune1241.yaml
world_languages/tests/data/tuwa1243.yaml
world_languages/tests/data/unse1236.yaml
world_languages/tests/data/wich1263.yaml
world_languages/tests/data/zza.yaml