Metadata-Version: 1.1
Name: django-world-languages
Version: 0.1
Summary: Languages and dialects of the world for Django projects
Home-page: https://github.com/blag/django-world-languages
Author: Blag
Author-email: blag@users.noreply.github.com
License: BSD
Keywords: languages,dialects,linguistics
Platform: UNKNOWN
Classifier: Development Status :: 3 - Alpha
Classifier: Environment :: Web Environment
Classifier: Intended Audience :: Science/Research
Classifier: License :: OSI Approved :: BSD License
Classifier: Operating System :: OS Independent
Classifier: Programming Language :: Python :: 3
Classifier: Topic :: Internet :: WWW/HTTP
Classifier: Topic :: Scientific/Engineering :: Information Analysis
Classifier: Topic :: Software Development :: Libraries :: Python Modules
Classifier: Topic :: Text Processing :: Linguistic
